{
  "request_id": "220509150623_6fdfcc11-1d8c-55cc-ad2f-affbfd1507f1",
  "status": "ready",
  "request": {
    "target_credentials": "e358cddc-2288-4da7-bb61-87f7203cee79",
    "source_settings": {
      "$schema": "https://s.y42.com/integrations/sql_model/0.0.0/source"
    },
    "table_settings": {
      "$schema": "https://s.y42.com/integrations/sql_model/0.0.0/table"
    },
    "created_at": "2022-05-09T15:06:23.621673+00:00",
    "target": {
      "storage": {
        "type": "githubapp",
        "path": "/src/Models/meta_fix_sql/table_1",
        "id": "6:1475cb08-028e-49db-b8e9-5171eb6b87af",
        "branch": "main"
      },
      "info": {
        "app_id": "24758422",
        "owner": "ronozoro",
        "repo": "git-data-mock-dev-cluster",
        "commit_sha": "afd2879d394de48e2a22c54e0d1e9d3552716e45"
      }
    },
    "context": {
      "company_id": 6,
      "company_slug": "y42-demo",
      "triggered_by_type": "user",
      "triggered_by_id": "10",
      "trial": false
    }
  },
  "created_at": "2022-05-09T15:06:23.621673+00:00",
  "finished_at": "2022-05-09T15:06:41.374065+00:00",
  "details": {
    "invalid_rows": 0,
    "import_finished_at": "2022-05-09T15:06:41.373931+00:00",
    "row_count": 100,
    "current_import_row_count": 100,
    "size_in_bytes": 13425,
    "external_id": "5eebb50f-d2ff-40dd-a395-fbf736b667b5",
    "columns": [
      {
        "field_name": "total_profit",
        "data_type": "FLOAT",
        "external_data_type": "FLOAT"
      },
      {
        "field_name": "id",
        "data_type": "INTEGER",
        "external_data_type": "INTEGER"
      },
      {
        "field_name": "total_revenue",
        "data_type": "FLOAT",
        "external_data_type": "FLOAT"
      },
      {
        "field_name": "total_cost",
        "data_type": "FLOAT",
        "external_data_type": "FLOAT"
      },
      {
        "field_name": "region",
        "data_type": "STRING",
        "external_data_type": "STRING"
      },
      {
        "field_name": "order_date",
        "data_type": "STRING",
        "external_data_type": "STRING"
      },
      {
        "field_name": "sales_channel",
        "data_type": "STRING",
        "external_data_type": "STRING"
      },
      {
        "field_name": "order_priority",
        "data_type": "STRING",
        "external_data_type": "STRING"
      },
      {
        "field_name": "unit_cost",
        "data_type": "FLOAT",
        "external_data_type": "FLOAT"
      },
      {
        "field_name": "sdc_deleted_at",
        "data_type": "INTEGER",
        "external_data_type": "INTEGER"
      },
      {
        "field_name": "sdc_extracted_at",
        "data_type": "FLOAT",
        "external_data_type": "FLOAT"
      },
      {
        "field_name": "ship_date",
        "data_type": "STRING",
        "external_data_type": "STRING"
      },
      {
        "field_name": "order_id",
        "data_type": "INTEGER",
        "external_data_type": "INTEGER"
      },
      {
        "field_name": "type",
        "data_type": "STRING",
        "external_data_type": "STRING"
      },
      {
        "field_name": "unit_price",
        "data_type": "FLOAT",
        "external_data_type": "FLOAT"
      },
      {
        "field_name": "units_sold",
        "data_type": "INTEGER",
        "external_data_type": "INTEGER"
      },
      {
        "field_name": "item",
        "data_type": "STRING",
        "external_data_type": "STRING"
      },
      {
        "field_name": "country",
        "data_type": "STRING",
        "external_data_type": "STRING"
      }
    ],
    "table_name": "220509150623_6fdfcc11-1d8c-55cc-ad2f-affbfd1507f1",
    "external_url": "https://console.cloud.google.com/bigquery?p=datos-tech&d=bigquery_dataset_git_data_mock_dev_cluster&t=220509150623_6fdfcc11-1d8c-55cc-ad2f-affbfd1507f1&page=table"
  },
  "_signature": "Y+Kgf6Lb3NI0FST0IdKJDpkoRE+bl3NBJQWdeiz5DJRJAdALyMxNbvcuFRqvjIFUx2WFPOzk0U9Xm8O+keslAQ=="
}
